<?xml version="1.0" encoding="utf-8"?>
<manifest xmlns="http://tizen.org/ns/packages" package="native-battery-monitor-tests" version="0.1.0" api-version="6.0">
	<label>NativeBatteryMonitorTest</label>
	<author email="test@tizen.org" href="www.tizen.org">test</author>
	<description>Native API test Application</description>
	<ui-application appid="native.battery-monitor-tests" exec="/usr/apps/native-battery-monitor-tests/bin/tct-battery-monitor-native" nodisplay="false" multiple="false" type="capp" taskmanage="false">
		<background-category value="background-network"/>
		<background-category value="download"/>
		<background-category value="iot-communication"/>
		<background-category value="location"/>
		<background-category value="media"/>
		<background-category value="sensor"/>
	</ui-application>
	<privileges>
		<privilege>http://tizen.org/privilege/systemmonitor</privilege>
	</privileges>
</manifest>
